<?xml version="1.0" encoding="UTF-8"?>

<ruleset name="Best Practices"
    xmlns="http://pmd.sourceforge.net/ruleset/2.0.0"
    xmlns:xsi="http://www.w3.org/2001/XMLSchema-instance"
    xsi:schemaLocation="http://pmd.sourceforge.net/ruleset/2.0.0 https://pmd.sourceforge.io/ruleset_2_0_0.xsd">

    <description>
Rules which enforce generally accepted best practices.
    </description>

    <rule name="AvoidMessageDigestField"
          language="kotlin"
          since="7.x"
          message="MessageDigest fields are not thread-safe; declare a local instance instead."
          class="net.sourceforge.pmd.lang.rule.xpath.XPathRule"
          externalInfoUrl="${pmd.website.baseurl}/pmd_rules_kotlin_bestpractices.html#avoidmessagedigestfield">
        <description>
            java.security.MessageDigest is not thread-safe. Declaring it as a class field exposes
            it to concurrent access without explicit synchronisation, producing incorrect digests.
            Create a new instance per method call, or protect shared access with a mutex.

            Note: this rule requires kotlin-type-mapper pre-analysis to be available.
            See the pmd-kotlin documentation for setup instructions.

            Kotlin equivalent of Java rule: category/java/bestpractices.xml/AvoidMessageDigestField
        </description>
        <priority>2</priority>
        <properties>
            <property name="javaEquivalentRule" type="String"
                      description="Java rule this Kotlin rule is based on; update this rule when the Java rule changes."
                      value="category/java/bestpractices.xml/AvoidMessageDigestField"/>
            <property name="xpath">
                <value><![CDATA[
//PropertyDeclaration[
    not(ancestor::FunctionBody)
    and pmd-kotlin:typeIs('java.security.MessageDigest')
]
                ]]></value>
            </property>
        </properties>
        <example><![CDATA[
import java.security.MessageDigest

class Bad {
    private val md: MessageDigest = MessageDigest.getInstance("SHA-256") // violation

    fun hash(data: ByteArray): ByteArray {
        md.reset()
        return md.digest(data) // race condition if called from multiple threads
    }
}

class Good {
    fun hash(data: ByteArray): ByteArray {
        val md = MessageDigest.getInstance("SHA-256") // ok: new instance per call
        return md.digest(data)
    }
}
        ]]></example>
    </rule>

    <rule name="AvoidPrintStackTrace"
          language="kotlin"
          since="7.x"
          message="Avoid printStackTrace(); use a logger call instead."
          class="net.sourceforge.pmd.lang.rule.xpath.XPathRule"
          externalInfoUrl="${pmd.website.baseurl}/pmd_rules_kotlin_bestpractices.html#avoidprintstacktrace">
        <description>
            Avoid calling Throwable.printStackTrace(); use a proper logger (e.g. SLF4J, Log4j2) instead.
            Stack traces printed to standard output can be lost in production and carry no log level,
            making them hard to control or suppress.

            Kotlin equivalent of Java rule: category/java/bestpractices.xml/AvoidPrintStackTrace
        </description>
        <priority>3</priority>
        <properties>
            <property name="javaEquivalentRule" type="String"
                      description="Java rule this Kotlin rule is based on; update this rule when the Java rule changes."
                      value="category/java/bestpractices.xml/AvoidPrintStackTrace"/>
            <property name="xpath">
                <value><![CDATA[
//PostfixUnaryExpression[pmd-kotlin:matchesSig('java.lang.Throwable#printStackTrace(*)')]
                ]]></value>
            </property>
        </properties>
        <example><![CDATA[
class Bad {
    fun handle() {
        try {
            riskyOperation()
        } catch (e: Exception) {
            e.printStackTrace() // violation: use logger instead
        }
    }
}

class Good {
    private val log = org.slf4j.LoggerFactory.getLogger(Good::class.java)

    fun handle() {
        try {
            riskyOperation()
        } catch (e: Exception) {
            log.error("riskyOperation failed", e) // ok
        }
    }
}
        ]]></example>
    </rule>

    <rule name="AvoidStringBufferField"
          language="kotlin"
          since="7.x"
          message="StringBuffer/StringBuilder fields can grow large and become a source of memory leaks."
          class="net.sourceforge.pmd.lang.rule.xpath.XPathRule"
          externalInfoUrl="${pmd.website.baseurl}/pmd_rules_kotlin_bestpractices.html#avoidstringbufferfield">
        <description>
            StringBuffer and StringBuilder instances can grow considerably and, if held as class
            fields across long-lived objects, may cause memory leaks. Prefer creating a local
            instance inside the method that needs it, or use String concatenation / string templates
            which the Kotlin compiler optimises automatically.

            Note: this rule requires kotlin-type-mapper pre-analysis to be available.
            See the pmd-kotlin documentation for setup instructions.

            Kotlin equivalent of Java rule: category/java/bestpractices.xml/AvoidStringBufferField
        </description>
        <priority>3</priority>
        <properties>
            <property name="javaEquivalentRule" type="String"
                      description="Java rule this Kotlin rule is based on; update this rule when the Java rule changes."
                      value="category/java/bestpractices.xml/AvoidStringBufferField"/>
            <property name="xpath">
                <value><![CDATA[
//PropertyDeclaration[
    not(ancestor::FunctionBody)
    and (pmd-kotlin:typeIs('java.lang.StringBuffer')
      or pmd-kotlin:typeIs('java.lang.StringBuilder'))
]
                ]]></value>
            </property>
        </properties>
        <example><![CDATA[
class Bad {
    private val sb: StringBuffer = StringBuffer()   // violation: potential memory leak

    fun append(s: String) = sb.append(s)
}

class Good {
    fun buildMessage(parts: List<String>): String {
        val sb = StringBuilder()                    // ok: local variable
        parts.forEach { sb.append(it) }
        return sb.toString()
    }
}
        ]]></example>
    </rule>

    <rule name="FunctionNameTooShort"
          since="7.0.0"
          language="kotlin"
          message="Function names should have non-cryptic and clear names."
          class="net.sourceforge.pmd.lang.rule.xpath.XPathRule"
          externalInfoUrl="${pmd.website.baseurl}/pmd_rules_kotlin_bestpractices.html#functionnametooshort">
        <description>
            Function names should be easy to understand and describe the intention. Makes developers happy.
        </description>
        <priority>3</priority>
        <properties>
            <property name="xpath">
                <value><![CDATA[
                    //FunctionDeclaration/SimpleIdentifier/T-Identifier[string-length(@Text) < 3]
                ]]></value>
            </property>
        </properties>
        <example>
            <![CDATA[
fun cl() {} // violation, no unavailable attribute added to the function declaration

fun calculateLayout() // no violation
]]>
        </example>
    </rule>

    <rule name="SystemPrintln"
          language="kotlin"
          since="7.x"
          message="Usage of System.out/err print methods; use a proper logger instead."
          class="net.sourceforge.pmd.lang.rule.xpath.XPathRule"
          externalInfoUrl="${pmd.website.baseurl}/pmd_rules_kotlin_bestpractices.html#systemprintln">
        <description>
            Calls to System.out.print*, System.err.print*, or System.out.printf are typically
            left-over debug statements. Use a proper logging framework (SLF4J, Log4j2, kotlin-logging)
            so output can be controlled by log level and configuration without redeploying.

            Note: this rule requires kotlin-type-mapper pre-analysis to be available.
            See the pmd-kotlin documentation for setup instructions.

            Kotlin equivalent of Java rule: category/java/bestpractices.xml/SystemPrintln
        </description>
        <priority>2</priority>
        <properties>
            <property name="javaEquivalentRule" type="String"
                      description="Java rule this Kotlin rule is based on; update this rule when the Java rule changes."
                      value="category/java/bestpractices.xml/SystemPrintln"/>
            <property name="xpath">
                <value><![CDATA[
//PostfixUnaryExpression[
    pmd-kotlin:matchesSig('java.io.PrintStream#println(*)')
    or pmd-kotlin:matchesSig('java.io.PrintStream#print(*)')
    or pmd-kotlin:matchesSig('java.io.PrintStream#printf(*)')
]
                ]]></value>
            </property>
        </properties>
        <example><![CDATA[
class Bad {
    fun report(msg: String) {
        System.out.println(msg)       // violation
        System.err.println("error!")  // violation
    }
}

class Good {
    private val log = org.slf4j.LoggerFactory.getLogger(Good::class.java)

    fun report(msg: String) {
        log.info(msg)  // ok
    }
}
        ]]></example>
    </rule>

</ruleset>
